mapsud/__init__.py
mapsud/graph.py
test/__init__.py
test/test.py
mapsud-0.0.1.dist-info/METADATA
mapsud-0.0.1.dist-info/WHEEL
mapsud-0.0.1.dist-info/top_level.txt
mapsud-0.0.1.dist-info/RECORD
