Metadata-Version: 2.1
Name: mapsud
Version: 0.0.1
Summary: voir presentation
Home-page: https://github.com/lucea97217/mapsud.git
Author: LUCEA, VALDEYRON, YUAN
Author-email: lenny.lucea@etu.umontpellier.fr
Maintainer: LUCEA, VALDEYRON, YUAN
Maintainer-email: lenny.lucea@etu.umontpellier.fr
License: MIT
Keywords: Tarifs autoroutiers sud France
Platform: ALL
